setup.cfg
setup.py
hellosign/__init__.py
hellosign/api.py
hellosign/hello_objects.py
hellosign/hellosign.py
hellosign.egg-info/PKG-INFO
hellosign.egg-info/SOURCES.txt
hellosign.egg-info/dependency_links.txt
hellosign.egg-info/not-zip-safe
hellosign.egg-info/requires.txt
hellosign.egg-info/top_level.txt