Metadata-Version: 1.0
Name: hellosign
Version: 0.1.0
Summary: Module for interacting with the HelloSign service
Home-page: https://github.com/rosscdh/hellosign
Author: Ross Crawford-d'Heureuse
Author-email: sendrossemail@gmail.com
License: UNKNOWN
Download-URL: https://github.com/rosscdh/hellosign/archive/0.1.1.tar.gz
Platform: UNKNOWN
